lanus/__init__.py
lanus/lanus.pyz
lanus-1.1.0.dist-info/METADATA
lanus-1.1.0.dist-info/WHEEL
lanus-1.1.0.dist-info/top_level.txt
lanus-1.1.0.dist-info/RECORD
