Metadata-Version: 2.1
Name: lanus
Version: 1.1.0
Summary: a basic package
Author: kubet
Author-email: kubet@atomicmail.io
License: Apache License 2.0
